odoo/addons/sale_order_line_clone/README.rst
odoo/addons/sale_order_line_clone/__init__.py
odoo/addons/sale_order_line_clone/__manifest__.py
odoo/addons/sale_order_line_clone/i18n/es.po
odoo/addons/sale_order_line_clone/models/__init__.py
odoo/addons/sale_order_line_clone/models/product_template.py
odoo/addons/sale_order_line_clone/models/sale_order.py
odoo/addons/sale_order_line_clone/security/sale_order_line_clone_security.xml
odoo/addons/sale_order_line_clone/static/description/icon.png
odoo/addons/sale_order_line_clone/static/description/index.html
odoo/addons/sale_order_line_clone/views/product_template_view.xml
odoo/addons/sale_order_line_clone/views/sale_order_view.xml
odoo_addon_sale_order_line_clone-15.0.1.0.0.dist-info/METADATA
odoo_addon_sale_order_line_clone-15.0.1.0.0.dist-info/WHEEL
odoo_addon_sale_order_line_clone-15.0.1.0.0.dist-info/top_level.txt
odoo_addon_sale_order_line_clone-15.0.1.0.0.dist-info/RECORD
