Metadata-Version: 2.1
Name: odoo-addon-sale_order_line_clone
Version: 15.0.1.0.0
Requires-Python: >=3.8
Requires-Dist: odoo>=15.0a,<15.1dev
Summary: Clone sale order lines.
Home-page: https://github.com/sygel-technology/sy-sale-workflow
License: AGPL-3
Author: Sygel, Odoo Community Association (OCA)
Author-email: support@odoo-community.org
Classifier: Programming Language :: Python
Classifier: Framework :: Odoo
Classifier: Framework :: Odoo :: 15.0
Classifier: License :: OSI Approved :: GNU Affero General Public License v3
